linguaml/__init__.py
linguaml-0.0.1.dist-info/METADATA
linguaml-0.0.1.dist-info/WHEEL
linguaml-0.0.1.dist-info/top_level.txt
linguaml-0.0.1.dist-info/RECORD
