Metadata-Version: 2.1
Name: linguaml
Version: 0.0.1
Summary: A project that combines the power of Large Language Models (LLMs) with traditional automated machine learning (AML) techniques.
Author-email: Isaac Fei <isaac.omega.fei@gmail.com>
Project-URL: Homepage, https://github.com/Isaac-Fate/LinguAML
Requires-Python: >=3.11
